pattoo_shared/__init__.py
pattoo_shared/agent.py
pattoo_shared/configuration.py
pattoo_shared/constants.py
pattoo_shared/converter.py
pattoo_shared/daemon.py
pattoo_shared/data.py
pattoo_shared/encrypt.py
pattoo_shared/errors.py
pattoo_shared/files.py
pattoo_shared/log.py
pattoo_shared/network.py
pattoo_shared/phttp.py
pattoo_shared/times.py
pattoo_shared/url.py
pattoo_shared/variables.py
pattoo_shared/installation/__init__.py
pattoo_shared/installation/configure.py
pattoo_shared/installation/environment.py
pattoo_shared/installation/packages.py
pattoo_shared/installation/shared.py
pattoo_shared/installation/systemd.py
tests/__init__.py
tests/libraries/__init__.py
tests/libraries/configuration.py
tests/libraries/general.py
tests/pattoo_shared_/__init__.py
tests/pattoo_shared_/test_agent.py
tests/pattoo_shared_/test_configuration.py
tests/pattoo_shared_/test_constants.py
tests/pattoo_shared_/test_converter.py
tests/pattoo_shared_/test_daemon.py
tests/pattoo_shared_/test_data.py
tests/pattoo_shared_/test_encrypt.py
tests/pattoo_shared_/test_files.py
tests/pattoo_shared_/test_log.py
tests/pattoo_shared_/test_network.py
tests/pattoo_shared_/test_phttp.py
tests/pattoo_shared_/test_times.py
tests/pattoo_shared_/test_variables.py
tests/pattoo_shared_/installation/__init__.py
tests/pattoo_shared_/installation/test_configure.py
tests/pattoo_shared_/installation/test_environment.py
tests/pattoo_shared_/installation/test_packages.py
tests/pattoo_shared_/installation/test_shared.py
tests/pattoo_shared_/installation/test_systemd.py
PattooShared-0.0.120.dist-info/LICENSE
PattooShared-0.0.120.dist-info/METADATA
PattooShared-0.0.120.dist-info/WHEEL
PattooShared-0.0.120.dist-info/top_level.txt
PattooShared-0.0.120.dist-info/RECORD
