Metadata-Version: 2.1
Name: PattooShared
Version: 0.0.120
Summary: Shared libraries for Pattoo Servers and Agents.
Home-page: https://github.com/PalisadoesFoundation/pattoo-shared
Author: Peter Harrison
Author-email: peter@palisadoes.org
Maintainer: Peter Harrison
Maintainer-email: peter@palisadoes.org
License: GPLv3+
Download-URL: https://github.com/PalisadoesFoundation/pattoo-shared
Platform: UNKNOWN
Requires-Python: >=3.6
Requires-Dist: PyYaml
Requires-Dist: distro
Requires-Dist: virtualenv (==20.0.30)
